andor3/__init__.py
andor3/andor3.py
andor3/constants.py
andor3/error.py
andor3/utils.py
andor3-0.3.4.dist-info/LICENSE
andor3-0.3.4.dist-info/METADATA
andor3-0.3.4.dist-info/WHEEL
andor3-0.3.4.dist-info/top_level.txt
andor3-0.3.4.dist-info/RECORD
