Metadata-Version: 2.1
Name: andor3
Version: 0.3.4
Summary: Interface to Andor s-CMOS cameras which communicate using the SDK3.
Home-page: https://gitlab.com/ptapping/andor3
Author: Patrick Tapping
Author-email: mail@patricktapping.com
Project-URL: Documentation, https://andor3.readthedocs.io/
Project-URL: Source, https://gitlab.com/ptapping/andor3
Project-URL: Tracker, https://gitlab.com/ptapping/andor3/-/issues
Classifier: Programming Language :: Python :: 3
Classifier: License :: OSI Approved :: GNU General Public License v3 or later (GPLv3+)
Classifier: Operating System :: OS Independent
Requires-Python: >=3.6
License-File: LICENSE
